qc_baselib/__init__.py
qc_baselib/configuration.py
qc_baselib/models/__init__.py
qc_baselib/models/common.py
qc_baselib/models/config.py
qc_baselib/models/result.py
qc_baselib/result.py
asam_qc_baselib-1.0.0.dist-info/LICENSE
asam_qc_baselib-1.0.0.dist-info/LICENSES/3rd_party_terms_and_licenses/Black_LICENSE
asam_qc_baselib-1.0.0.dist-info/LICENSES/3rd_party_terms_and_licenses/Lxml_LICENSE
asam_qc_baselib-1.0.0.dist-info/LICENSES/3rd_party_terms_and_licenses/Pydantic_LICENSE
asam_qc_baselib-1.0.0.dist-info/LICENSES/3rd_party_terms_and_licenses/Pydanticxml_LICENSE
asam_qc_baselib-1.0.0.dist-info/LICENSES/3rd_party_terms_and_licenses/Pytest_LICENSE
asam_qc_baselib-1.0.0.dist-info/LICENSES/readme.md
asam_qc_baselib-1.0.0.dist-info/METADATA
asam_qc_baselib-1.0.0.dist-info/WHEEL
asam_qc_baselib-1.0.0.dist-info/RECORD
