Metadata-Version: 2.1
Name: asam-qc-baselib
Version: 1.0.0
Summary: Python base library for ASAM Quality Checker Framework
License: MPL-2.0
Author: Patrick Abrahão
Author-email: patrick@ivex.ai
Requires-Python: >=3.10,<4.0
Classifier: License :: OSI Approved
Classifier: Programming Language :: Python :: 3
Classifier: Programming Language :: Python :: 3.10
Classifier: Programming Language :: Python :: 3.11
Classifier: Programming Language :: Python :: 3.12
Classifier: Programming Language :: Python :: 3.13
Requires-Dist: lxml (>=5.2.2,<6.0.0)
Requires-Dist: pydantic (>=2.7.2,<3.0.0)
Requires-Dist: pydantic-xml (>=2.11.0,<3.0.0)
